blastbesties/__init__.py
blastbesties/_version.py
blastbesties/app.py
blastbesties/blastops.py
blastbesties/logs.py
blastbesties/utils.py
blastbesties-1.2.0.dist-info/METADATA
blastbesties-1.2.0.dist-info/WHEEL
blastbesties-1.2.0.dist-info/entry_points.txt
blastbesties-1.2.0.dist-info/licenses/LICENSE
blastbesties-1.2.0.dist-info/RECORD
