Metadata-Version: 2.3
Name: blastbesties
Version: 1.2.0
Summary: Rapid discovery of reciprocal best blast pairs from BLAST output files.
Project-URL: homepage, https://github.com/adamtaranto/blast-besties
Project-URL: documentation, https://github.com/adamtaranto/blast-besties
Project-URL: repository, https://github.com/adamtaranto/blast-besties
Author-email: Adam Taranto <adam.p.taranto@gmail.com>
License: MIT
License-File: LICENSE
Classifier: Intended Audience :: Science/Research
Classifier: License :: OSI Approved :: MIT License
Classifier: Programming Language :: Python :: 3
Classifier: Topic :: Scientific/Engineering :: Bio-Informatics
Requires-Python: >=3.8
Requires-Dist: argparse-tui
Provides-Extra: tests
Requires-Dist: pytest; extra == 'tests'
